Workbook

Sheet Portada
B1: MATRIZ DE TRAZABILIDAD · FERREMAX (FMX)
B3: Documento | C3: FMX_MT.xlsx — Matriz de Trazabilidad RF ↔ CUS
B4: Versión | C4: 1.1
B5: Fecha de consolidación | C5: 16/09/2026
B6: Actividad del cronograma | C6: Consolidación de la matriz de trazabilidad RF ↔ CUS
B7: Hito | C7: Hito 1 — Inicio y Requisitos
B8: Responsable | C8: Vegas Villalva
B9: Grupo | C9: Grupo 2
B10: Proyecto | C10: FERREMAX — Sistema Web de Gestión para Ferretería
B11: Curso | C11: Gestión de la Configuración y Mantenimiento del Software · UNMSM · FISI · E.P. de Ingeniería de Software · Docente: Lenis Rossi Wong Portillo
B12: Fuentes | C12: DOCUMENTACIÓN DE FERREMAX (RF y RNF) · FMX_AS.docx · FMX_CU1.docx a FMX_CU9.docx
B14: PROPÓSITO
B15: Esta matriz relaciona cada requisito del sistema con el caso de uso que lo realiza. Sirve para tres cosas:
B16: 1) Comprobar que ningún requisito quedó sin implementar (cobertura hacia adelante).
B17: 2) Comprobar que ningún caso de uso existe sin un requisito que lo justifique (cobertura hacia atrás).
B18: 3) Medir el impacto de un cambio: al modificar un RF se sabe de inmediato qué casos de uso, qué documentos
B19: y qué casos de prueba hay que revisar.
B21: LEYENDA DE LA MATRIZ
B22: X | C22: Realización principal: el caso de uso implementa el requisito.
B23: o | C23: Participación de soporte: el caso de uso usa o depende del requisito, sin ser su dueño.
C24: Celda vacía: no existe relación entre el requisito y el caso de uso.
B26: CONTENIDO DEL LIBRO
B27: RF ↔ CUS | C27: Matriz cruzada de los 29 requisitos funcionales contra los 9 casos de uso.
B28: RNF ↔ CUS | C28: Matriz cruzada de los 19 requisitos no funcionales contra los 9 casos de uso.
B29: PN ↔ CUS | C29: Relación entre los 3 procesos de negocio y los casos de uso que los automatizan.
B30: CUS ↔ Entrega | C30: Responsable, documento, rama y paquete de cada caso de uso.
B31: CUS ↔ Pruebas | C31: Casos de prueba previstos para el Hito 3, por caso de uso.
B32: Cobertura | C32: Análisis de cobertura calculado con fórmulas sobre las hojas anteriores.

Sheet RF ↔ CUS
B1: MATRIZ DE TRAZABILIDAD · REQUISITOS FUNCIONALES ↔ CASOS DE USO
B2: X = realización principal · o = participación de soporte
B4: Código | C4: Requisito funcional | D4: Descripción | E4: Módulo | F4: CUS-01 | G4: CUS-02 | H4: CUS-03 | I4: CUS-04 | J4: CUS-05 | K4: CUS-06 | L4: CUS-07 | M4: CUS-08 | N4: CUS-09 | O4: Nº de CUS | P4: Estado
B5: RF-01 | C5: Iniciar sesión | D5: Autenticación de administradores y vendedores mediante nombre de usuario y contraseña. | E5: Autenticación | F5: X | O5: =COUNTIF(F5:N5,"X")+COUNTIF(F5:N5,"o") -> 1 | P5: =IF(COUNTIF(F5:N5,"X")=0,"SIN COBERTURA","Cubierto") -> Cubierto
B6: RF-02 | C6: Cerrar sesión | D6: Cierre seguro de la sesión del usuario. | E6: Autenticación | G6: X | O6: =COUNTIF(F6:N6,"X")+COUNTIF(F6:N6,"o") -> 1 | P6: =IF(COUNTIF(F6:N6,"X")=0,"SIN COBERTURA","Cubierto") -> Cubierto
B7: RF-03 | C7: Control de acceso por roles | D7: Muestra únicamente las opciones que corresponden al rol del usuario autenticado. | E7: Autenticación | F7: X | H7: o | I7: o | J7: o | K7: o | L7: o | M7: o | N7: o | O7: =COUNTIF(F7:N7,"X")+COUNTIF(F7:N7,"o") -> 8 | P7: =IF(COUNTIF(F7:N7,"X")=0,"SIN COBERTURA","Cubierto") -> Cubierto
B8: RF-04 | C8: Bloqueo por intentos fallidos | D8: Bloqueo temporal de 5 minutos tras 3 intentos fallidos de inicio de sesión. | E8: Autenticación | F8: X | O8: =COUNTIF(F8:N8,"X")+COUNTIF(F8:N8,"o") -> 1 | P8: =IF(COUNTIF(F8:N8,"X")=0,"SIN COBERTURA","Cubierto") -> Cubierto
B9: RF-05 | C9: Registrar producto | D9: Alta de un producto con nombre, proveedor, cantidad inicial, precio, categoría y ubicación. | E9: Productos | H9: X | O9: =COUNTIF(F9:N9,"X")+COUNTIF(F9:N9,"o") -> 1 | P9: =IF(COUNTIF(F9:N9,"X")=0,"SIN COBERTURA","Cubierto") -> Cubierto
B10: RF-06 | C10: Modificar producto | D10: Edición de los datos de un producto existente. | E10: Productos | H10: X | O10: =COUNTIF(F10:N10,"X")+COUNTIF(F10:N10,"o") -> 1 | P10: =IF(COUNTIF(F10:N10,"X")=0,"SIN COBERTURA","Cubierto") -> Cubierto
B11: RF-07 | C11: Eliminar producto | D11: Baja del producto: física si no tiene movimientos, lógica si los tiene. | E11: Productos | H11: X | O11: =COUNTIF(F11:N11,"X")+COUNTIF(F11:N11,"o") -> 1 | P11: =IF(COUNTIF(F11:N11,"X")=0,"SIN COBERTURA","Cubierto") -> Cubierto
B12: RF-08 | C12: Consultar productos | D12: Búsqueda de productos por nombre, categoría o proveedor. | E12: Productos | H12: X | I12: o | O12: =COUNTIF(F12:N12,"X")+COUNTIF(F12:N12,"o") -> 2 | P12: =IF(COUNTIF(F12:N12,"X")=0,"SIN COBERTURA","Cubierto") -> Cubierto
B13: RF-09 | C13: Control de stock mínimo | D13: Definición de un stock mínimo por producto y alerta al alcanzarlo. | E13: Productos | H13: X | L13: o | O13: =COUNTIF(F13:N13,"X")+COUNTIF(F13:N13,"o") -> 2 | P13: =IF(COUNTIF(F13:N13,"X")=0,"SIN COBERTURA","Cubierto") -> Cubierto
B14: RF-10 | C14: Realizar venta | D14: Registro de una venta seleccionando productos y cantidades. | E14: Ventas | I14: X | O14: =COUNTIF(F14:N14,"X")+COUNTIF(F14:N14,"o") -> 1 | P14: =IF(COUNTIF(F14:N14,"X")=0,"SIN COBERTURA","Cubierto") -> Cubierto
B15: RF-11 | C15: Cálculo automático de totales | D15: Cálculo del subtotal, los impuestos y el total de la venta. | E15: Ventas | I15: X | J15: o | O15: =COUNTIF(F15:N15,"X")+COUNTIF(F15:N15,"o") -> 2 | P15: =IF(COUNTIF(F15:N15,"X")=0,"SIN COBERTURA","Cubierto") -> Cubierto
B16: RF-12 | C16: Verificar stock disponible | D16: Validación de que la cantidad solicitada no supere el stock disponible. | E16: Ventas | H16: o | I16: X | O16: =COUNTIF(F16:N16,"X")+COUNTIF(F16:N16,"o") -> 2 | P16: =IF(COUNTIF(F16:N16,"X")=0,"SIN COBERTURA","Cubierto") -> Cubierto
B17: RF-13 | C17: Generar factura | D17: Emisión automática de la factura con número, fecha, productos, importes y vendedor. | E17: Ventas | I17: X | J17: o | O17: =COUNTIF(F17:N17,"X")+COUNTIF(F17:N17,"o") -> 2 | P17: =IF(COUNTIF(F17:N17,"X")=0,"SIN COBERTURA","Cubierto") -> Cubierto
B18: RF-14 | C18: Imprimir factura | D18: Impresión de la factura generada desde el navegador. | E18: Ventas | J18: X | O18: =COUNTIF(F18:N18,"X")+COUNTIF(F18:N18,"o") -> 1 | P18: =IF(COUNTIF(F18:N18,"X")=0,"SIN COBERTURA","Cubierto") -> Cubierto
B19: RF-15 | C19: Historial de ventas | D19: Registro de cada venta con fecha, hora, vendedor, productos y total, para su consulta. | E19: Ventas | I19: o | K19: X | O19: =COUNTIF(F19:N19,"X")+COUNTIF(F19:N19,"o") -> 2 | P19: =IF(COUNTIF(F19:N19,"X")=0,"SIN COBERTURA","Cubierto") -> Cubierto
B20: RF-16 | C20: Actualización de stock por venta | D20: Reducción automática del stock de cada producto al confirmar la venta. | E20: Inventario | I20: X | L20: o | O20: =COUNTIF(F20:N20,"X")+COUNTIF(F20:N20,"o") -> 2 | P20: =IF(COUNTIF(F20:N20,"X")=0,"SIN COBERTURA","Cubierto") -> Cubierto
B21: RF-17 | C21: Actualización de stock por compra | D21: Incremento automático del stock al registrar una entrada por compra. | E21: Inventario | H21: X | L21: o | O21: =COUNTIF(F21:N21,"X")+COUNTIF(F21:N21,"o") -> 2 | P21: =IF(COUNTIF(F21:N21,"X")=0,"SIN COBERTURA","Cubierto") -> Cubierto
B22: RF-18 | C22: Consultar stock actual | D22: Consulta del stock disponible de todos los productos o de uno específico. | E22: Inventario | H22: X | I22: o | O22: =COUNTIF(F22:N22,"X")+COUNTIF(F22:N22,"o") -> 2 | P22: =IF(COUNTIF(F22:N22,"X")=0,"SIN COBERTURA","Cubierto") -> Cubierto
B23: RF-19 | C23: Imprimir lista de stock | D23: Reporte imprimible o exportable con el listado de productos, cantidades, precios y valor. | E23: Inventario | H23: X | O23: =COUNTIF(F23:N23,"X")+COUNTIF(F23:N23,"o") -> 1 | P23: =IF(COUNTIF(F23:N23,"X")=0,"SIN COBERTURA","Cubierto") -> Cubierto
B24: RF-20 | C24: Alertas de stock bajo | D24: Indicador visual cuando un producto tiene stock igual o inferior al mínimo. | E24: Inventario | H24: o | L24: X | O24: =COUNTIF(F24:N24,"X")+COUNTIF(F24:N24,"o") -> 2 | P24: =IF(COUNTIF(F24:N24,"X")=0,"SIN COBERTURA","Cubierto") -> Cubierto
B25: RF-21 | C25: Reporte de ventas por período | D25: Reporte de ventas totales por día, semana, mes o rango personalizado. | E25: Reportes | N25: X | O25: =COUNTIF(F25:N25,"X")+COUNTIF(F25:N25,"o") -> 1 | P25: =IF(COUNTIF(F25:N25,"X")=0,"SIN COBERTURA","Cubierto") -> Cubierto
B26: RF-22 | C26: Ver productos más vendidos | D26: Gráfico de barras con los 5 productos más vendidos del rango seleccionado. | E26: Reportes | N26: X | O26: =COUNTIF(F26:N26,"X")+COUNTIF(F26:N26,"o") -> 1 | P26: =IF(COUNTIF(F26:N26,"X")=0,"SIN COBERTURA","Cubierto") -> Cubierto
B27: RF-23 | C27: Ver productos menos vendidos | D27: Gráfico de barras con los 5 productos menos vendidos, excluyendo los que no registran ventas. | E27: Reportes | N27: X | O27: =COUNTIF(F27:N27,"X")+COUNTIF(F27:N27,"o") -> 1 | P27: =IF(COUNTIF(F27:N27,"X")=0,"SIN COBERTURA","Cubierto") -> Cubierto
B28: RF-24 | C28: Exportar reportes | D28: Exportación de los reportes de ventas a PDF o CSV. | E28: Reportes | K28: o | L28: o | N28: X | O28: =COUNTIF(F28:N28,"X")+COUNTIF(F28:N28,"o") -> 3 | P28: =IF(COUNTIF(F28:N28,"X")=0,"SIN COBERTURA","Cubierto") -> Cubierto
B29: RF-25 | C29: Filtrar reportes por vendedor | D29: Filtrado de los reportes de ventas por vendedor, además del período. | E29: Reportes | K29: X | N29: o | O29: =COUNTIF(F29:N29,"X")+COUNTIF(F29:N29,"o") -> 2 | P29: =IF(COUNTIF(F29:N29,"X")=0,"SIN COBERTURA","Cubierto") -> Cubierto
B30: RF-26 | C30: Registrar usuario | D30: Creación de usuarios con rol vendedor, asignando nombre de usuario y contraseña. | E30: Usuarios | M30: X | O30: =COUNTIF(F30:N30,"X")+COUNTIF(F30:N30,"o") -> 1 | P30: =IF(COUNTIF(F30:N30,"X")=0,"SIN COBERTURA","Cubierto") -> Cubierto
B31: RF-27 | C31: Eliminar usuario | D31: Baja lógica de un usuario, impidiendo su acceso futuro. | E31: Usuarios | M31: X | O31: =COUNTIF(F31:N31,"X")+COUNTIF(F31:N31,"o") -> 1 | P31: =IF(COUNTIF(F31:N31,"X")=0,"SIN COBERTURA","Cubierto") -> Cubierto
B32: RF-28 | C32: Listar usuarios | D32: Listado de los usuarios registrados con su nombre y su rol. | E32: Usuarios | M32: X | O32: =COUNTIF(F32:N32,"X")+COUNTIF(F32:N32,"o") -> 1 | P32: =IF(COUNTIF(F32:N32,"X")=0,"SIN COBERTURA","Cubierto") -> Cubierto
B33: RF-29 | C33: Cambiar contraseña | D33: Cambio de la contraseña propia por parte de cualquier usuario autenticado. | E33: Usuarios | M33: X | O33: =COUNTIF(F33:N33,"X")+COUNTIF(F33:N33,"o") -> 1 | P33: =IF(COUNTIF(F33:N33,"X")=0,"SIN COBERTURA","Cubierto") -> Cubierto
D34: REQUISITOS POR CASO DE USO → | F34: =COUNTIF(F5:F33,"X") -> 3 | G34: =COUNTIF(G5:G33,"X") -> 1 | H34: =COUNTIF(H5:H33,"X") -> 8 | I34: =COUNTIF(I5:I33,"X") -> 5 | J34: =COUNTIF(J5:J33,"X") -> 1 | K34: =COUNTIF(K5:K33,"X") -> 2 | L34: =COUNTIF(L5:L33,"X") -> 1 | M34: =COUNTIF(M5:M33,"X") -> 4 | N34: =COUNTIF(N5:N33,"X") -> 4 | O34: =SUM(F34:N34) -> 29

Sheet RNF ↔ CUS
B1: MATRIZ DE TRAZABILIDAD · REQUISITOS NO FUNCIONALES ↔ CASOS DE USO
B2: X = el requisito restringe directamente ese caso de uso · TODOS = restricción transversal a todo el sistema
B4: Código | C4: Requisito no funcional | D4: Categoría | E4: Criterio de aceptación | F4: CUS-01 | G4: CUS-02 | H4: CUS-03 | I4: CUS-04 | J4: CUS-05 | K4: CUS-06 | L4: CUS-07 | M4: CUS-08 | N4: CUS-09 | O4: Nº de CUS
B5: RNF-01 | C5: Tiempo de respuesta en ventas | D5: Rendimiento | E5: Menos de 2 segundos entre la confirmación de la venta y la factura en pantalla. | I5: X | J5: X | O5: =COUNTIF(F5:N5,"X") -> 2
B6: RNF-02 | C6: Tiempo de respuesta en reportes | D6: Rendimiento | E6: Menos de 5 segundos para un reporte de un mes. | K6: X | L6: X | N6: X | O6: =COUNTIF(F6:N6,"X") -> 3
B7: RNF-03 | C7: Concurrencia | D7: Rendimiento | E7: Soporte de al menos 3 vendedores operando de forma simultánea. | H7: X | I7: X | O7: =COUNTIF(F7:N7,"X") -> 2
B8: RNF-04 | C8: Disponibilidad | D8: Rendimiento | E8: 99 % de tiempo operativo durante el horario de atención. | F8: X | G8: X | H8: X | I8: X | J8: X | K8: X | L8: X | M8: X | N8: X | O8: =COUNTIF(F8:N8,"X") -> 9
B9: RNF-05 | C9: Encriptación de contraseñas | D9: Seguridad | E9: Almacenamiento de contraseñas con hash seguro (bcrypt). | F9: X | M9: X | O9: =COUNTIF(F9:N9,"X") -> 2
B10: RNF-06 | C10: Protección contra inyección SQL | D10: Seguridad | E10: Consultas parametrizadas o ORM en todo acceso a datos. | F10: X | G10: X | H10: X | I10: X | J10: X | K10: X | L10: X | M10: X | N10: X | O10: =COUNTIF(F10:N10,"X") -> 9
B11: RNF-07 | C11: Protección de sesiones | D11: Seguridad | E11: Expiración automática de la sesión tras 30 minutos de inactividad. | F11: X | G11: X | O11: =COUNTIF(F11:N11,"X") -> 2
B12: RNF-08 | C12: Registro de auditoría | D12: Seguridad | E12: Log de cada venta con vendedor, fecha y hora. | I12: X | L12: X | M12: X | O12: =COUNTIF(F12:N12,"X") -> 3
B13: RNF-09 | C13: Interfaz intuitiva | D13: Usabilidad | E13: Interfaz clara, con botones grandes y etiquetas visibles. | F13: X | G13: X | H13: X | I13: X | J13: X | K13: X | L13: X | M13: X | N13: X | O13: =COUNTIF(F13:N13,"X") -> 9
B14: RNF-10 | C14: Accesibilidad desde navegadores | D14: Usabilidad | E14: Compatibilidad con versiones recientes de Chrome, Firefox y Edge. | F14: X | G14: X | H14: X | I14: X | J14: X | K14: X | L14: X | M14: X | N14: X | O14: =COUNTIF(F14:N14,"X") -> 9
B15: RNF-11 | C15: Diseño responsivo | D15: Usabilidad | E15: Adaptación de la interfaz al tamaño de pantalla en tabletas. | F15: X | G15: X | H15: X | I15: X | J15: X | K15: X | L15: X | M15: X | N15: X | O15: =COUNTIF(F15:N15,"X") -> 9
B16: RNF-12 | C16: Mensajes de error claros | D16: Usabilidad | E16: Mensajes descriptivos y orientados a la acción del usuario. | F16: X | H16: X | I16: X | M16: X | O16: =COUNTIF(F16:N16,"X") -> 4
B17: RNF-13 | C17: Arquitectura MVC | D17: Mantenibilidad | E17: Separación de la lógica de negocio, la interfaz y el control de flujo. | F17: X | G17: X | H17: X | I17: X | J17: X | K17: X | L17: X | M17: X | N17: X | O17: =COUNTIF(F17:N17,"X") -> 9
B18: RNF-14 | C18: Código documentado | D18: Mantenibilidad | E18: Comentarios y documentación básica en el código fuente. | F18: X | G18: X | H18: X | I18: X | J18: X | K18: X | L18: X | M18: X | N18: X | O18: =COUNTIF(F18:N18,"X") -> 9
B19: RNF-15 | C19: Portabilidad | D19: Mantenibilidad | E19: Ejecución en servidor local Windows o Linux y, en el futuro, en la nube. | F19: X | G19: X | H19: X | I19: X | J19: X | K19: X | L19: X | M19: X | N19: X | O19: =COUNTIF(F19:N19,"X") -> 9
B20: RNF-16 | C20: Integridad de datos | D20: Confiabilidad | E20: Sin stock negativo ni ventas parcialmente registradas. | H20: X | I20: X | L20: X | O20: =COUNTIF(F20:N20,"X") -> 3
B21: RNF-17 | C21: Respaldo de información | D21: Confiabilidad | E21: Mecanismo de respaldo periódico de la base de datos. | F21: X | G21: X | H21: X | I21: X | J21: X | K21: X | L21: X | M21: X | N21: X | O21: =COUNTIF(F21:N21,"X") -> 9
B22: RNF-18 | C22: Interfaz web | D22: Interfaz | E22: Acceso mediante navegador, sin instalar software adicional. | F22: X | G22: X | H22: X | I22: X | J22: X | K22: X | L22: X | M22: X | N22: X | O22: =COUNTIF(F22:N22,"X") -> 9
B23: RNF-19 | C23: Impresión desde navegador | D23: Interfaz | E23: Impresión de facturas y reportes con la función nativa del navegador. | H23: X | J23: X | L23: X | N23: X | O23: =COUNTIF(F23:N23,"X") -> 4

Sheet PN ↔ CUS
B1: MATRIZ DE TRAZABILIDAD · PROCESOS DE NEGOCIO ↔ CASOS DE USO
B2: Origen: Documento de Negocio (FMX_DN.docx). X = el caso de uso automatiza una actividad de ese proceso.
B4: Código | C4: Proceso de negocio | D4: Descripción | E4: CUS-01 | F4: CUS-02 | G4: CUS-03 | H4: CUS-04 | I4: CUS-05 | J4: CUS-06 | K4: CUS-07 | L4: CUS-08 | M4: CUS-09 | N4: Nº de CUS
B5: PN1 | C5: Venta al cliente | D5: Atención en mostrador, cobro y emisión del comprobante. | H5: X | I5: X | J5: X | N5: =COUNTIF(E5:M5,"X") -> 3
B6: PN2 | C6: Gestión de inventario | D6: Conteo, reposición y control de las existencias del almacén. | G6: X | K6: X | N6: =COUNTIF(E6:M6,"X") -> 2
B7: PN3 | C7: Administración y análisis | D7: Gestión del personal del negocio y análisis de los resultados de venta. | E7: X | F7: X | L7: X | M7: X | N7: =COUNTIF(E7:M7,"X") -> 4
B9: CASOS DE USO SIN PROCESO DE NEGOCIO ASOCIADO
D10: Estado de cada caso de uso → | E10: =IF(COUNTIF(E5:E7,"X")=0,"HUÉRFANO","OK") -> OK | F10: =IF(COUNTIF(F5:F7,"X")=0,"HUÉRFANO","OK") -> OK | G10: =IF(COUNTIF(G5:G7,"X")=0,"HUÉRFANO","OK") -> OK | H10: =IF(COUNTIF(H5:H7,"X")=0,"HUÉRFANO","OK") -> OK | I10: =IF(COUNTIF(I5:I7,"X")=0,"HUÉRFANO","OK") -> OK | J10: =IF(COUNTIF(J5:J7,"X")=0,"HUÉRFANO","OK") -> OK | K10: =IF(COUNTIF(K5:K7,"X")=0,"HUÉRFANO","OK") -> OK | L10: =IF(COUNTIF(L5:L7,"X")=0,"HUÉRFANO","OK") -> OK | M10: =IF(COUNTIF(M5:M7,"X")=0,"HUÉRFANO","OK") -> OK

Sheet CUS ↔ Entrega
B1: TRAZABILIDAD DE ENTREGA · CASO DE USO ↔ RESPONSABLE, DOCUMENTO Y RAMA
B2: Origen: cronograma FMX_CDP.xlsx, actividades del Hito 1 y del Hito 2.
B4: Caso de uso | C4: Nombre | D4: Paquete | E4: Responsable | F4: Documento de especificación | G4: Rama en GitHub | H4: Requisitos funcionales
B5: CUS-01 | C5: Iniciar sesión | D5: Seguridad | E5: Castillejo Huancas | F5: FMX_CU1.docx | G5: feature/cu_1 | H5: RF-01, RF-03, RF-04
B6: CUS-02 | C6: Cerrar sesión | D6: Seguridad | E6: Castillejo Huancas | F6: FMX_CU2.docx | G6: feature/cu_2 | H6: RF-02
B7: CUS-03 | C7: Mantener productos | D7: Inventario | E7: Mallqui Meza | F7: FMX_CU3.docx | G7: feature/cu_3 | H7: RF-05, RF-06, RF-07, RF-08, RF-09, RF-17, RF-18, RF-19
B8: CUS-04 | C8: Registrar venta | D8: Ventas | E8: Cordero Alfaro | F8: FMX_CU4.docx | G8: feature/cu_4 | H8: RF-10, RF-11, RF-12, RF-13, RF-16
B9: CUS-05 | C9: Consultar factura | D9: Ventas | E9: Cordero Alfaro | F9: FMX_CU5.docx | G9: feature/cu_5 | H9: RF-14
B10: CUS-06 | C10: Consultar historial de ventas | D10: Reportes | E10: Alegre Mayanga | F10: FMX_CU6.docx | G10: feature/cu_6 | H10: RF-15, RF-25
B11: CUS-07 | C11: Consultar movimientos de stock | D11: Inventario | E11: Mallqui Meza | F11: FMX_CU7.docx | G11: feature/cu_7 | H11: RF-20
B12: CUS-08 | C12: Mantener usuarios | D12: Administración | E12: Roman Hurtado | F12: FMX_CU8.docx | G12: feature/cu_8 | H12: RF-26, RF-27, RF-28, RF-29
B13: CUS-09 | C13: Generar reportes de ventas | D13: Reportes | E13: Roman Hurtado | F13: FMX_CU9.docx | G13: feature/cu_9 | H13: RF-21, RF-22, RF-23, RF-24

Sheet CUS ↔ Pruebas
B1: TRAZABILIDAD DE VERIFICACIÓN · CASO DE USO ↔ CASOS DE PRUEBA
B2: Estos casos de prueba se ejecutan en el Hito 3. Registre el resultado en la columna «Resultado» (celdas de fondo amarillo).
B4: ID | C4: Caso de uso | D4: Escenario de prueba | E4: Tipo | F4: Resultado esperado | G4: Resultado
B5: CP-01 | C5: CUS-01 | D5: Ingreso con credenciales válidas | E5: Funcional | F5: El usuario accede y el menú corresponde a su rol. | G5: Pendiente
B6: CP-02 | C6: CUS-01 | D6: Ingreso con credenciales incorrectas | E6: Funcional | F6: Se rechaza el acceso con mensaje genérico, sin revelar qué campo falló. | G6: Pendiente
B7: CP-03 | C7: CUS-01 | D7: Bloqueo tras tres intentos fallidos | E7: Seguridad | F7: El cuarto intento se rechaza sin validar credenciales. | G7: Pendiente
B8: CP-04 | C8: CUS-01 | D8: Acceso denegado por rol a una ruta de administración | E8: Seguridad | F8: Un vendedor recibe error 403 al invocar la ruta directamente. | G8: Pendiente
B9: CP-05 | C9: CUS-02 | D9: Cierre de sesión e invalidación en el servidor | E9: Seguridad | F9: Tras salir, ninguna ruta protegida responde sin autenticarse de nuevo. | G9: Pendiente
B10: CP-06 | C10: CUS-02 | D10: Expiración de la sesión por inactividad | E10: Seguridad | F10: A los 30 minutos sin actividad la sesión se cierra automáticamente. | G10: Pendiente
B11: CP-07 | C11: CUS-03 | D11: Alta de producto con movimiento de entrada | E11: Funcional | F11: El producto queda activo y se registra su movimiento de stock. | G11: Pendiente
B12: CP-08 | C12: CUS-03 | D12: Baja lógica de un producto con ventas asociadas | E12: Funcional | F12: El producto se desactiva y conserva su historial. | G12: Pendiente
B13: CP-09 | C13: CUS-03 | D13: Rechazo de producto duplicado | E13: Funcional | F13: No se admite otro producto activo con el mismo nombre y proveedor. | G13: Pendiente
B14: CP-10 | C14: CUS-03 | D14: Alerta al quedar por debajo del stock mínimo | E14: Funcional | F14: El producto aparece marcado como stock bajo. | G14: Pendiente
B15: CP-11 | C15: CUS-04 | D15: Venta de varios productos con cálculo de IGV | E15: Funcional | F15: Subtotal, IGV del 18 % y total correctos, redondeados a dos decimales. | G15: Pendiente
... B33: CP-29 | C33: CUS-09 | D33: Reporte mensual dentro del límite de tiempo | E33: Rendimiento | F33: El reporte de un mes se genera en menos de 5 segundos. | G33: Pendiente

Sheet Cobertura
B1: ANÁLISIS DE COBERTURA DE LA TRAZABILIDAD
B2: Todos los valores se calculan con fórmulas sobre las hojas anteriores: si cambia la matriz, cambian solos.
B4: Indicador | C4: Valor | D4: Lectura
B5: Requisitos funcionales especificados | C5: =COUNTA('RF ↔ CUS'!$B$5:$B$33) -> 29 | D5: Total de RF declarados en la documentación del sistema.
B6: Requisitos funcionales con caso de uso asignado | C6: =COUNTIF('RF ↔ CUS'!$P$5:$P$33,"Cubierto") -> 29 | D6: RF que tienen al menos una realización principal (X).
B7: Requisitos funcionales sin cobertura | C7: =COUNTIF('RF ↔ CUS'!$P$5:$P$33,"SIN COBERTURA") -> 0 | D7: Debe ser 0. Cualquier otro valor señala un RF que nadie implementa.
B8: Cobertura de requisitos funcionales | C8: =IF(C5=0,0,C6/C5) -> 1 | D8: Porcentaje de RF cubiertos por algún caso de uso.
B9: Casos de uso especificados | C9: =COUNTA('CUS ↔ Entrega'!$B$5:$B$13) -> 9 | D9: Total de CUS del sistema.
B10: Casos de uso sin requisito funcional asociado | C10: =COUNTIF('RF ↔ CUS'!$F$34:$N$34,0) -> 0 | D10: Debe ser 0. Un CUS sin RF es funcionalidad que nadie pidió.
B11: Requisitos no funcionales especificados | C11: =COUNTA('RNF ↔ CUS'!$B$5:$B$23) -> 19 | D11: Total de RNF declarados en la documentación.
B12: Requisitos no funcionales sin caso de uso asociado | C12: =COUNTIF('RNF ↔ CUS'!$O$5:$O$23,0) -> 0 | D12: RNF que no restringen ningún CUS en concreto.
B13: Procesos de negocio modelados | C13: =COUNTA('PN ↔ CUS'!$B$5:$B$7) -> 3 | D13: Procesos AS-IS levantados en el Documento de Negocio.
B14: Casos de prueba previstos | C14: =COUNTA('CUS ↔ Pruebas'!$B$5:$B$33) -> 29 | D14: Casos de prueba diseñados para el Hito 3.
B15: Casos de prueba conformes | C15: =COUNTIF('CUS ↔ Pruebas'!$G$5:$G$33,"Conforme") -> 0 | D15: Se actualiza al registrar los resultados en la hoja «CUS ↔ Pruebas».
B16: Avance de la verificación | C16: =IF(C14=0,0,C15/C14) -> 0 | D16: Porcentaje de casos de prueba con resultado conforme.
B18: REQUISITOS FUNCIONALES POR CASO DE USO
B19: Caso de uso | C19: Nº de RF | D19: Requisitos funcionales que realiza
B20: CUS-01 — Iniciar sesión | C20: ='RF ↔ CUS'!F34 -> 3 | D20: RF-01, RF-03, RF-04
B21: CUS-02 — Cerrar sesión | C21: ='RF ↔ CUS'!G34 -> 1 | D21: RF-02
B22: CUS-03 — Mantener productos | C22: ='RF ↔ CUS'!H34 -> 8 | D22: RF-05, RF-06, RF-07, RF-08, RF-09, RF-17, RF-18, RF-19
B23: CUS-04 — Registrar venta | C23: ='RF ↔ CUS'!I34 -> 5 | D23: RF-10, RF-11, RF-12, RF-13, RF-16
B24: CUS-05 — Consultar factura | C24: ='RF ↔ CUS'!J34 -> 1 | D24: RF-14
B25: CUS-06 — Consultar historial de ventas | C25: ='RF ↔ CUS'!K34 -> 2 | D25: RF-15, RF-25
B26: CUS-07 — Consultar movimientos de stock | C26: ='RF ↔ CUS'!L34 -> 1 | D26: RF-20
B27: CUS-08 — Mantener usuarios | C27: ='RF ↔ CUS'!M34 -> 4 | D27: RF-26, RF-27, RF-28, RF-29
B28: CUS-09 — Generar reportes de ventas | C28: ='RF ↔ CUS'!N34 -> 4 | D28: RF-21, RF-22, RF-23, RF-24
B31: Nota: la columna «Nº de RF» cuenta solo las realizaciones principales (X). Las participaciones de soporte (o) no se suman aquí para no contar dos veces un mismo requisito.
